vui/__init__.py
vui/event.py
vui/layout.py
vui/observable.py
vui/pane.py
vui/test_layout.py
vui/test_observable.py
vui/test_pane.py
vui/test_view.py
vui/view.py
vui-0.0.4.dist-info/LICENSE
vui-0.0.4.dist-info/METADATA
vui-0.0.4.dist-info/WHEEL
vui-0.0.4.dist-info/top_level.txt
vui-0.0.4.dist-info/RECORD
