Metadata-Version: 2.1
Name: vui
Version: 0.0.4
Summary: GUI framework written in pure Python
Home-page: https://github.com/eterevsky/vui
Author: Oleg Eterevsky
Author-email: oleg@eterevsky.com
License: UNKNOWN
Platform: UNKNOWN
Classifier: Programming Language :: Python :: 3
Classifier: License :: OSI Approved :: MIT License
Classifier: Operating System :: OS Independent
Classifier: Development Status :: 2 - Pre-Alpha
Requires-Python: >=3.6
Requires-Dist: pyglet (>=1.5.6)
